Metadata-Version: 2.1
Name: ai-logicplum
Version: 1.2.8
Requires-Dist: requests
Requires-Dist: pandas
Requires-Dist: Pillow
